knock_knock/Bxb1_layout.py
knock_knock/__init__.py
knock_knock/arrayed_experiment_group.py
knock_knock/blast.py
knock_knock/build_targets.py
knock_knock/common_sequences.py
knock_knock/example_data/data/illumina/BCAP31_ultramer_R1.fastq.gz
knock_knock/example_data/data/illumina/BCAP31_ultramer_R2.fastq.gz
knock_knock/example_data/data/illumina/CLTA_PCR_R1.fastq.gz
knock_knock/example_data/data/illumina/CLTA_PCR_R2.fastq.gz
knock_knock/example_data/data/illumina/sample_sheet.csv
knock_knock/example_data/data/pacbio/RAB11A_PCR.fastq.gz
knock_knock/example_data/data/pacbio/RAB11A_plasmid.fastq.gz
knock_knock/example_data/data/pacbio/sample_sheet.csv
knock_knock/example_data/index_locations.yaml
knock_knock/example_data/targets/amplicon_primers.csv
knock_knock/example_data/targets/donors.csv
knock_knock/example_data/targets/sgRNAs.csv
knock_knock/example_data/targets/targets.csv
knock_knock/experiment.py
knock_knock/experiment_group.py
knock_knock/explore.py
knock_knock/illumina_experiment.py
knock_knock/integrases.py
knock_knock/knock.py
knock_knock/layout.py
knock_knock/length_bias_experiment.py
knock_knock/logo_v2.png
knock_knock/outcome.py
knock_knock/outcome_record.py
knock_knock/pacbio_experiment.py
knock_knock/paired_end_experiment.py
knock_knock/parallel.py
knock_knock/pegRNAs.py
knock_knock/prime_editing_experiment.py
knock_knock/prime_editing_layout.py
knock_knock/range_picker.py
knock_knock/ranges.py
knock_knock/svg.py
knock_knock/table.py
knock_knock/table_template/conf.json
knock_knock/table_template/table.html.j2
knock_knock/target_info.py
knock_knock/test/.gitignore
knock_knock/test/conftest.py
knock_knock/test/indices/bosTau7/STAR/chrLength.txt
knock_knock/test/indices/bosTau7/STAR/chrName.txt
knock_knock/test/indices/e_coli/STAR/chrLength.txt
knock_knock/test/indices/e_coli/STAR/chrName.txt
knock_knock/test/indices/hg19/STAR/chrLength.txt
knock_knock/test/indices/hg19/STAR/chrName.txt
knock_knock/test/indices/hg38/STAR/chrLength.txt
knock_knock_x-0.1.0.dist-info/LICENSE
knock_knock_x-0.1.0.dist-info/WHEEL
knock_knock_x-0.1.0.dist-info/entry_points.txt
knock_knock_x-0.1.0.dist-info/METADATA
knock_knock_x-0.1.0.dist-info/RECORD
