Metadata-Version: 2.1
Name: knock-knock-x
Version: 0.1.0
Summary: A modified version of Jeff's knock-knock.
License: GNU General Public License v3.0
Author: hukai916
Author-email: 31452631+hukai916@users.noreply.github.com
Requires-Python: >=3.8,<4.0
Classifier: License :: Other/Proprietary License
Classifier: Programming Language :: Python :: 3
Classifier: Programming Language :: Python :: 3.8
Classifier: Programming Language :: Python :: 3.9
Classifier: Programming Language :: Python :: 3.10
Classifier: Programming Language :: Python :: 3.11
Requires-Dist: Pillow (>=9.4.0,<10.0.0)
Requires-Dist: PyYAML (>=6.0,<7.0)
Requires-Dist: biopython (>=1.81,<2.0)
Requires-Dist: bokeh (>=3.0.3,<4.0.0)
Requires-Dist: h5py (>=3.8.0,<4.0.0)
Requires-Dist: hits (>=0.3.3,<0.4.0)
Requires-Dist: ipywidgets (>=8.0.4,<9.0.0)
Requires-Dist: matplotlib (>=3.7.0,<4.0.0)
Requires-Dist: nbconvert (>=7.2.9,<8.0.0)
Requires-Dist: nbformat (>=5.7.3,<6.0.0)
Requires-Dist: numpy (>=1.24.2,<2.0.0)
Requires-Dist: pandas (>=1.5.3,<2.0.0)
Requires-Dist: pysam (>=0.20.0,<0.21.0)
Requires-Dist: tqdm (>=4.64.1,<5.0.0)
